[
  {
      "id": 1388534235400000,
      "author": "Yoda Jedi Master",
      "text": "I say words backwards. No more traning do you require"
  },
  {
      "id": 14200704235200000,
      "author": "Han Solo",
      "text": "I have a bad feeling about this"
  },
  {
      "id": 14592252591632254,
      "author": "Luke Skywalker",
      "text": "May the force be with you"
  },
  {
      "id": 14123322252254,
      "author": "Terminator 3",
      "text": "I will be back"
  },
  {
      "id": 1412454332254,
      "author": "Princess Leah",
      "text": "Get this walking carpet out of my sight"
  },
  {
      "id": 1412454399999932254,
      "author": "Indiana Jones",
      "text": "Shorty, you are from Shanghai"
  },
  {
      "id": 1422232342454399999932254,
      "author": "Alien Marsian",
      "text": "Home, call home"
  }
]
